qlivi/__init__.py
qlivi/__main__.py
qlivi/cli/__init__.py
qlivi/cli/commands.py
qlivi-0.3.0.dist-info/LICENSE
qlivi-0.3.0.dist-info/WHEEL
qlivi-0.3.0.dist-info/METADATA
qlivi-0.3.0.dist-info/RECORD
