Metadata-Version: 2.1
Name: qlivi
Version: 0.3.0
Summary: dd
License: MPL-2.0
Author: musangtara
Author-email: musangtara@gmail.com
Requires-Python: >=3.7.1,<4.0.0
Classifier: License :: OSI Approved
Classifier: Programming Language :: Python :: 3
Classifier: Programming Language :: Python :: 3.8
Classifier: Programming Language :: Python :: 3.9
Requires-Dist: click (>=8.0.1,<9.0.0)
Requires-Dist: pandas (>=1.3.2,<2.0.0)
Requires-Dist: requests (>=2.26.0,<3.0.0)
